{"layout":[{"component":"row","params":"{}","stateId":"row-3474023-default-1","version":1,"vertical":"layout","widgetTrackingInfo":"{\"name\":\"layout.row\", \"vertical\":\"layout\", \"component\":\"row\", \"version\":1, \"id\":3474023, \"revisionId\":3917164}","placeholders":[{"name":"default","widgets":[{"component":"column","params":"{}","stateId":"column-3474022-default-1","version":1,"vertical":"layout","widgetTrackingInfo":"{\"name\":\"layout.column\", \"vertical\":\"layout\", \"component\":\"column\", \"version\":1, \"id\":3474022, \"revisionId\":3917163}","placeholders":[{"name":"default","widgets":[{"component":"skuGrid","params":"{\"title\":\"Рекомендуем для вас\",\"disablePagination\":true}","stateId":"skuGrid-3534901-default-1","version":1,"vertical":"products","widgetTrackingInfo":"{\"name\":\"shelf.apparelPersonalSuggest\", \"vertical\":\"products\", \"component\":\"skuGrid\", \"version\":1, \"originName\":\"shelf.apparelPersonalSuggest\", \"originVertical\":\"shelf\", \"originComponent\":\"apparelPersonalSuggest\", \"originVersion\":2, \"id\":3534901, \"configId\":82345, \"configDtId\":77914, \"revisionId\":4000047, \"index\":5, \"dtName\":\"sku.grid\"}","widgetToken":"0BRM1YBXFAlX3ZXgYaA4QlxtcgDuiza3","timeSpent":75,"name":"shelf.apparelPersonalSuggest","id":3534901,"isTrackingOn":true}]}],"widgetToken":"0BRM1Tgy9oi3hBgE61REVb1y_KFMqqJ5","name":"layout.column","id":3474022,"isTrackingOn":true,"isStatic":true}]}],"widgetToken":"0BRM1Vo7GbccX0SjOZjgxNWE9SIiNHb9","name":"layout.row","id":3474023}],"widgetStates":{"skuGrid-3534901-default-1":"{\"header\":{\"title\":\"Рекомендуем для вас\"},\"productContainer\":{\"options\":{\"itemsAreFaded\":true, \"ratio\":\"3:4\", \"columnsCount\":4, \"withGaps\":false},\"products\":[{\"action\":{\"behavior\":\"BEHAVIOR_TYPE_REDIRECT\", \"link\":\"/product/zont-muzhskoy-avtomat-antiveter-1053059331/?at=16tL2xB9XswWRo8uqXqljLs3Dg4kyUQ3qk2BSKOr904\"},\"alt\":\"Зонт мужской автомат антиветер Рекомендуем для вас\",\"isAdult\":false,\"items\":[{\"type\":\"image\", \"image\":{\"link\":\"https://cdn1.ozone.ru/s3/multimedia-1-o/7393713540.jpg\", \"contentMode\":\"SCALE_ASPECT_FILL\"}}],\"link\":\"/product/zont-muzhskoy-avtomat-antiveter-1053059331/?at=16tL2xB9XswWRo8uqXqljLs3Dg4kyUQ3qk2BSKOr904\",\"shouldBlur\":false,\"skuId\":\"1053059331\",\"state\":[{\"type\":\"priceV2\", \"priceV2\":{\"price\":[{\"text\":\"512 ₽\", \"textStyle\":\"PRICE\"}, {\"text\":\"2 920 ₽\", \"textStyle\":\"ORIGINAL_PRICE\"}], \"discount\":\"−82%\", \"priceStyle\":{\"styleType\":\"SALE_PRICE\", \"gradient\":{\"startColor\":\"#F1117E\", \"endColor\":\"#F1117E\"}}, \"preset\":\"SIZE_500\", \"paddingBottom\":\"PADDING_200\"}},{\"type\":\"textAtom\", \"textAtom\":{\"text\":\"Зонт мужской автомат антиветер\", \"textStyle\":\"tsBodyL\", \"maxLines\":2, \"testInfo\":{\"automatizationId\":\"tile-name\"}}, \"id\":\"name\"}],\"trackingInfo\":{\"aux_click\":{\"actionType\":\"aux_click\", \"key\":\"16tL2xB9XswWRo8uqXqljLs3Dg4kyUQ3qk2BSKOr904\", \"custom\":{\"advertLite\":\"AD8CU5VKSVkoPeKx4bIQli5BXwXmDZUQUAGVPhVGjii9aXMZBUgEAkpX2vwaX2F1AI5-l4P1pUSswlEFpg\"}},\"click\":{\"actionType\":\"click\", \"key\":\"16tL2xB9XswWRo8uqXqljLs3Dg4kyUQ3qk2BSKOr904\", \"custom\":{\"advertLite\":\"AD8CU5VKSVkoPeKx4bIQli5BXwXmDZUQUAGVPhVGjii9aXMZBUgEAkpX2vwaX2F1AI5-l4P1pUSswlEFpg\"}},\"right_click\":{\"actionType\":\"right_click\", \"key\":\"16tL2xB9XswWRo8uqXqljLs3Dg4kyUQ3qk2BSKOr904\", \"custom\":{\"advertLite\":\"AD8CU5VKSVkoPeKx4bIQli5BXwXmDZUQUAGVPhVGjii9aXMZBUgEAkpX2vwaX2F1AI5-l4P1pUSswlEFpg\"}},\"view\":{\"actionType\":\"view\", \"key\":\"16tL2xB9XswWRo8uqXqljLs3Dg4kyUQ3qk2BSKOr904\"}}},{\"action\":{\"behavior\":\"BEHAVIOR_TYPE_REDIRECT\", \"link\":\"/product/kupalnik-razdelnyy-2391137418/\"},\"alt\":\"Купальник раздельный Рекомендуем для вас\",\"isAdult\":false,\"items\":[{\"type\":\"image\", \"image\":{\"link\":\"https://cdn1.ozone.ru/s3/multimedia-1-2/7416679070.jpg\", \"contentMode\":\"SCALE_ASPECT_FILL\"}}],\"link\":\"/product/kupalnik-razdelnyy-2391137418/\",\"shouldBlur\":false,\"skuId\":\"2391137418\",\"state\":[{\"type\":\"priceV2\", \"priceV2\":{\"price\":[{\"text\":\"849 ₽\", \"textStyle\":\"PRICE\"}, {\"text\":\"1 448 ₽\", \"textStyle\":\"ORIGINAL_PRICE\"}], \"discount\":\"−41%\", \"priceStyle\":{\"styleType\":\"CARD_PRICE\"}, \"preset\":\"SIZE_500\", \"paddingBottom\":\"PADDING_200\"}},{\"type\":\"textAtom\", \"textAtom\":{\"text\":\"Купальник раздельный\", \"textStyle\":\"tsBodyL\", \"maxLines\":2, \"testInfo\":{\"automatizationId\":\"tile-name\"}}, \"id\":\"name\"}],\"trackingInfo\":{\"aux_click\":{\"actionType\":\"aux_click\", \"key\":\"PjtJ89Nkncmk6jvqio30mpJhAEzGJ9ILoP7o0cnyBBwO\"},\"click\":{\"actionType\":\"click\", \"key\":\"PjtJ89Nkncmk6jvqio30mpJhAEzGJ9ILoP7o0cnyBBwO\"},\"right_click\":{\"actionType\":\"right_click\", \"key\":\"PjtJ89Nkncmk6jvqio30mpJhAEzGJ9ILoP7o0cnyBBwO\"},\"view\":{\"actionType\":\"view\", \"key\":\"PjtJ89Nkncmk6jvqio30mpJhAEzGJ9ILoP7o0cnyBBwO\"}}},{\"action\":{\"behavior\":\"BEHAVIOR_TYPE_REDIRECT\", \"link\":\"/product/cobra-remen-remen-1583837943/?at=WPtNRZXW8hvpBvPkum1xv0BTy1AyRmiZ4L9PXcQXlE2P\"},\"alt\":\"Cobra Ремень ремень Рекомендуем для вас\",\"isAdult\":false,\"items\":[{\"type\":\"image\", \"image\":{\"link\":\"https://cdn1.ozone.ru/s3/multimedia-1-0/7369187760.jpg\", \"contentMode\":\"SCALE_ASPECT_FILL\"}}],\"link\":\"/product/cobra-remen-remen-1583837943/?at=WPtNRZXW8hvpBvPkum1xv0BTy1AyRmiZ4L9PXcQXlE2P\",\"shouldBlur\":false,\"skuId\":\"1583837943\",\"state\":[{\"type\":\"priceV2\", \"priceV2\":{\"price\":[{\"text\":\"412 ₽\", \"textStyle\":\"PRICE\"}, {\"text\":\"2 000 ₽\", \"textStyle\":\"ORIGINAL_PRICE\"}], \"discount\":\"−79%\", \"priceStyle\":{\"styleType\":\"SALE_PRICE\", \"gradient\":{\"startColor\":\"#F1117E\", \"endColor\":\"#F1117E\"}}, \"preset\":\"SIZE_500\", \"paddingBottom\":\"PADDING_200\"}},{\"type\":\"textAtom\", \"textAtom\":{\"text\":\"3 329 шт осталось\", \"textStyle\":\"tsBodyControl400Small\", \"textColor\":\"textAccent\", \"maxLines\":1, \"testInfo\":{\"automatizationId\":\"tile-blackFridayStockbar\"}}},{\"type\":\"textAtom\", \"textAtom\":{\"text\":\"Cobra Ремень ремень\", \"textStyle\":\"tsBodyL\", \"maxLines\":2, \"testInfo\":{\"automatizationId\":\"tile-name\"}}, \"id\":\"name\"}],\"trackingInfo\":{\"aux_click\":{\"actionType\":\"aux_click\", \"key\":\"WPtNRZXW8hvpBvPkum1xv0BTy1AyRmiZ4L9PXcQXlE2P\", \"custom\":{\"advertLite\":\"AD8C_33lTOS4VH1Z2hZOQWa16hTkVqkjUUPedDkgIhE0uP2yGy7m1D4YSeLc5pzAlJ1oiIinxi2qvK9Coq4\"}},\"click\":{\"actionType\":\"click\", \"key\":\"WPtNRZXW8hvpBvPkum1xv0BTy1AyRmiZ4L9PXcQXlE2P\", \"custom\":{\"advertLite\":\"AD8C_33lTOS4VH1Z2hZOQWa16hTkVqkjUUPedDkgIhE0uP2yGy7m1D4YSeLc5pzAlJ1oiIinxi2qvK9Coq4\"}},\"right_click\":{\"actionType\":\"right_click\", \"key\":\"WPtNRZXW8hvpBvPkum1xv0BTy1AyRmiZ4L9PXcQXlE2P\", \"custom\":{\"advertLite\":\"AD8C_33lTOS4VH1Z2hZOQWa16hTkVqkjUUPedDkgIhE0uP2yGy7m1D4YSeLc5pzAlJ1oiIinxi2qvK9Coq4\"}},\"view\":{\"actionType\":\"view\", \"key\":\"WPtNRZXW8hvpBvPkum1xv0BTy1AyRmiZ4L9PXcQXlE2P\"}}},{\"action\":{\"behavior\":\"BEHAVIOR_TYPE_REDIRECT\", \"link\":\"/product/shorty-monsko-2038627735/?at=ywtAqK2R3IgzAw4QsqrMnKrT1J89Q3UNm3JAlc3RvJkv\"},\"alt\":\"Шорты MONSKO Рекомендуем для вас\",\"isAdult\":false,\"items\":[{\"type\":\"image\", \"image\":{\"link\":\"https://cdn1.ozone.ru/s3/multimedia-1-3/7478076963.jpg\", \"contentMode\":\"SCALE_ASPECT_FILL\"}}],\"link\":\"/product/shorty-monsko-2038627735/?at=ywtAqK2R3IgzAw4QsqrMnKrT1J89Q3UNm3JAlc3RvJkv\",\"shouldBlur\":false,\"skuId\":\"2038627735\",\"state\":[{\"type\":\"priceV2\", \"priceV2\":{\"price\":[{\"text\":\"840 ₽\", \"textStyle\":\"PRICE\"}, {\"text\":\"6 204 ₽\", \"textStyle\":\"ORIGINAL_PRICE\"}], \"discount\":\"−86%\", \"priceStyle\":{\"styleType\":\"SALE_PRICE\", \"gradient\":{\"startColor\":\"#F1117E\", \"endColor\":\"#F1117E\"}}, \"preset\":\"SIZE_500\", \"paddingBottom\":\"PADDING_200\"}},{\"type\":\"textAtom\", \"textAtom\":{\"text\":\"1 шт осталось\", \"textStyle\":\"tsBodyControl400Small\", \"textColor\":\"textAccent\", \"maxLines\":1, \"testInfo\":{\"automatizationId\":\"tile-blackFridayStockbar\"}}},{\"type\":\"textAtom\", \"textAtom\":{\"text\":\"Шорты MONSKO\", \"textStyle\":\"tsBodyL\", \"maxLines\":2, \"testInfo\":{\"automatizationId\":\"tile-name\"}}, \"id\":\"name\"}],\"trackingInfo\":{\"aux_click\":{\"actionType\":\"aux_click\", \"key\":\"ywtAqK2R3IgzAw4QsqrMnKrT1J89Q3UNm3JAlc3RvJkv\", \"custom\":{\"advertLite\":\"AD8CxKOvU1RqwbOwhf79QPLwQ3fUT7lZZQQ-3Wzz1Agq2dksSapO-6X6r0RFwPY_Fg1ei5i5DDWdSa2DeAo\"}},\"click\":{\"actionType\":\"click\", \"key\":\"ywtAqK2R3IgzAw4QsqrMnKrT1J89Q3UNm3JAlc3RvJkv\", \"custom\":{\"advertLite\":\"AD8CxKOvU1RqwbOwhf79QPLwQ3fUT7lZZQQ-3Wzz1Agq2dksSapO-6X6r0RFwPY_Fg1ei5i5DDWdSa2DeAo\"}},\"right_click\":{\"actionType\":\"right_click\", \"key\":\"ywtAqK2R3IgzAw4QsqrMnKrT1J89Q3UNm3JAlc3RvJkv\", \"custom\":{\"advertLite\":\"AD8CxKOvU1RqwbOwhf79QPLwQ3fUT7lZZQQ-3Wzz1Agq2dksSapO-6X6r0RFwPY_Fg1ei5i5DDWdSa2DeAo\"}},\"view\":{\"actionType\":\"view\", \"key\":\"ywtAqK2R3IgzAw4QsqrMnKrT1J89Q3UNm3JAlc3RvJkv\"}}},{\"action\":{\"behavior\":\"BEHAVIOR_TYPE_REDIRECT\", \"link\":\"/product/komplekt-belya-1556442624/?at=28t0PWZ9QSpknNvGfRw33wfzQYBE9svrPkv7IBZG3K5\"},\"alt\":\"Комплект белья Рекомендуем для вас\",\"isAdult\":false,\"items\":[{\"type\":\"image\", \"image\":{\"link\":\"https://cdn1.ozone.ru/s3/multimedia-1-v/7293022159.jpg\", \"contentMode\":\"SCALE_ASPECT_FILL\"}}],\"link\":\"/product/komplekt-belya-1556442624/?at=28t0PWZ9QSpknNvGfRw33wfzQYBE9svrPkv7IBZG3K5\",\"shouldBlur\":false,\"skuId\":\"1556442624\",\"state\":[{\"type\":\"priceV2\", \"priceV2\":{\"price\":[{\"text\":\"1 019 ₽\", \"textStyle\":\"PRICE\"}, {\"text\":\"5 999 ₽\", \"textStyle\":\"ORIGINAL_PRICE\"}], \"discount\":\"−83%\", \"priceStyle\":{\"styleType\":\"SALE_PRICE\", \"gradient\":{\"startColor\":\"#F1117E\", \"endColor\":\"#F1117E\"}}, \"preset\":\"SIZE_500\", \"paddingBottom\":\"PADDING_200\"}},{\"type\":\"textAtom\", \"textAtom\":{\"text\":\"43 шт осталось\", \"textStyle\":\"tsBodyControl400Small\", \"textColor\":\"textAccent\", \"maxLines\":1, \"testInfo\":{\"automatizationId\":\"tile-blackFridayStockbar\"}}},{\"type\":\"textAtom\", \"textAtom\":{\"text\":\"Комплект белья\", \"textStyle\":\"tsBodyL\", \"maxLines\":2, \"testInfo\":{\"automatizationId\":\"tile-name\"}}, \"id\":\"name\"}],\"trackingInfo\":{\"aux_click\":{\"actionType\":\"aux_click\", \"key\":\"28t0PWZ9QSpknNvGfRw33wfzQYBE9svrPkv7IBZG3K5\", \"custom\":{\"advertLite\":\"AD8CDiPdqzoMWfiANvcPi_QGtLhVD9VXpEAdUpAw0Uw_J1Lza4LOzGpns-mwxz42XsEXKMTH4wLg7DgcvA\"}},\"click\":{\"actionType\":\"click\", \"key\":\"28t0PWZ9QSpknNvGfRw33wfzQYBE9svrPkv7IBZG3K5\", \"custom\":{\"advertLite\":\"AD8CDiPdqzoMWfiANvcPi_QGtLhVD9VXpEAdUpAw0Uw_J1Lza4LOzGpns-mwxz42XsEXKMTH4wLg7DgcvA\"}},\"right_click\":{\"actionType\":\"right_click\", \"key\":\"28t0PWZ9QSpknNvGfRw33wfzQYBE9svrPkv7IBZG3K5\", \"custom\":{\"advertLite\":\"AD8CDiPdqzoMWfiANvcPi_QGtLhVD9VXpEAdUpAw0Uw_J1Lza4LOzGpns-mwxz42XsEXKMTH4wLg7DgcvA\"}},\"view\":{\"actionType\":\"view\", \"key\":\"28t0PWZ9QSpknNvGfRw33wfzQYBE9svrPkv7IBZG3K5\"}}},{\"action\":{\"behavior\":\"BEHAVIOR_TYPE_REDIRECT\", \"link\":\"/product/panama-hophay-536153667/?at=Rltyjo0zXIY7qMM0hBOlpRVs66gjmiVXpD2Pc0ogD1r\"},\"alt\":\"Панама Hophay Рекомендуем для вас\",\"isAdult\":false,\"items\":[{\"type\":\"image\", \"image\":{\"link\":\"https://cdn1.ozone.ru/s3/multimedia-1-h/7433814257.jpg\", \"contentMode\":\"SCALE_ASPECT_FILL\"}}],\"link\":\"/product/panama-hophay-536153667/?at=Rltyjo0zXIY7qMM0hBOlpRVs66gjmiVXpD2Pc0ogD1r\",\"shouldBlur\":false,\"skuId\":\"536153667\",\"state\":[{\"type\":\"priceV2\", \"priceV2\":{\"price\":[{\"text\":\"682 ₽\", \"textStyle\":\"PRICE\"}, {\"text\":\"2 600 ₽\", \"textStyle\":\"ORIGINAL_PRICE\"}], \"discount\":\"−73%\", \"priceStyle\":{\"styleType\":\"SALE_PRICE\", \"gradient\":{\"startColor\":\"#F1117E\", \"endColor\":\"#F1117E\"}}, \"preset\":\"SIZE_500\", \"paddingBottom\":\"PADDING_200\"}},{\"type\":\"textAtom\", \"textAtom\":{\"text\":\"10 шт осталось\", \"textStyle\":\"tsBodyControl400Small\", \"textColor\":\"textAccent\", \"maxLines\":1, \"testInfo\":{\"automatizationId\":\"tile-blackFridayStockbar\"}}},{\"type\":\"textAtom\", \"textAtom\":{\"text\":\"Панама Hophay\", \"textStyle\":\"tsBodyL\", \"maxLines\":2, \"testInfo\":{\"automatizationId\":\"tile-name\"}}, \"id\":\"name\"}],\"trackingInfo\":{\"aux_click\":{\"actionType\":\"aux_click\", \"key\":\"Rltyjo0zXIY7qMM0hBOlpRVs66gjmiVXpD2Pc0ogD1r\", \"custom\":{\"advertLite\":\"AD8Cif2Oi7YikheD8D4tMtXAC3SrcQlTiIE6phuxmPgrP4SyNEGy4BSNHKk8s6u8I4uApZYk33MyBrDxZw8\"}},\"click\":{\"actionType\":\"click\", \"key\":\"Rltyjo0zXIY7qMM0hBOlpRVs66gjmiVXpD2Pc0ogD1r\", \"custom\":{\"advertLite\":\"AD8Cif2Oi7YikheD8D4tMtXAC3SrcQlTiIE6phuxmPgrP4SyNEGy4BSNHKk8s6u8I4uApZYk33MyBrDxZw8\"}},\"right_click\":{\"actionType\":\"right_click\", \"key\":\"Rltyjo0zXIY7qMM0hBOlpRVs66gjmiVXpD2Pc0ogD1r\", \"custom\":{\"advertLite\":\"AD8Cif2Oi7YikheD8D4tMtXAC3SrcQlTiIE6phuxmPgrP4SyNEGy4BSNHKk8s6u8I4uApZYk33MyBrDxZw8\"}},\"view\":{\"actionType\":\"view\", \"key\":\"Rltyjo0zXIY7qMM0hBOlpRVs66gjmiVXpD2Pc0ogD1r\"}}},{\"action\":{\"behavior\":\"BEHAVIOR_TYPE_REDIRECT\", \"link\":\"/product/shumin-maska-dlya-sna-chernaya-1563221610/?at=MZtvMDkAYSDl22wJSoLQoPzUqGz0Z1FwM9365FA7RMWO\"},\"alt\":\"Shumin Маска для сна черная Рекомендуем для вас\",\"isAdult\":false,\"items\":[{\"type\":\"image\", \"image\":{\"link\":\"https://cdn1.ozone.ru/s3/multimedia-1-n/7417332419.jpg\", \"contentMode\":\"SCALE_ASPECT_FILL\"}}],\"link\":\"/product/shumin-maska-dlya-sna-chernaya-1563221610/?at=MZtvMDkAYSDl22wJSoLQoPzUqGz0Z1FwM9365FA7RMWO\",\"shouldBlur\":false,\"skuId\":\"1563221610\",\"state\":[{\"type\":\"priceV2\", \"priceV2\":{\"price\":[{\"text\":\"406 ₽\", \"textStyle\":\"PRICE\"}, {\"text\":\"1 290 ₽\", \"textStyle\":\"ORIGINAL_PRICE\"}], \"discount\":\"−68%\", \"priceStyle\":{\"styleType\":\"SALE_PRICE\", \"gradient\":{\"startColor\":\"#F1117E\", \"endColor\":\"#F1117E\"}}, \"preset\":\"SIZE_500\", \"paddingBottom\":\"PADDING_200\"}},{\"type\":\"textAtom\", \"textAtom\":{\"text\":\"Shumin Маска для сна черная\", \"textStyle\":\"tsBodyL\", \"maxLines\":2, \"testInfo\":{\"automatizationId\":\"tile-name\"}}, \"id\":\"name\"}],\"trackingInfo\":{\"aux_click\":{\"actionType\":\"aux_click\", \"key\":\"MZtvMDkAYSDl22wJSoLQoPzUqGz0Z1FwM9365FA7RMWO\", \"custom\":{\"advertLite\":\"AD8Cr5hczJhenHairdpQrJbLojVARh1t9Bg3bW2NMw7dN9lhPHJg3aKsg5Rm6x-H9FvCBrWSGRWGANFr-A\"}},\"click\":{\"actionType\":\"click\", \"key\":\"MZtvMDkAYSDl22wJSoLQoPzUqGz0Z1FwM9365FA7RMWO\", \"custom\":{\"advertLite\":\"AD8Cr5hczJhenHairdpQrJbLojVARh1t9Bg3bW2NMw7dN9lhPHJg3aKsg5Rm6x-H9FvCBrWSGRWGANFr-A\"}},\"right_click\":{\"actionType\":\"right_click\", \"key\":\"MZtvMDkAYSDl22wJSoLQoPzUqGz0Z1FwM9365FA7RMWO\", \"custom\":{\"advertLite\":\"AD8Cr5hczJhenHairdpQrJbLojVARh1t9Bg3bW2NMw7dN9lhPHJg3aKsg5Rm6x-H9FvCBrWSGRWGANFr-A\"}},\"view\":{\"actionType\":\"view\", \"key\":\"MZtvMDkAYSDl22wJSoLQoPzUqGz0Z1FwM9365FA7RMWO\"}}},{\"action\":{\"behavior\":\"BEHAVIOR_TYPE_REDIRECT\", \"link\":\"/product/h-gl-tsepochka-na-telo-iz-bisera-1893742906/\"},\"alt\":\"Högl Цепочка на тело Из бисера Рекомендуем для вас\",\"isAdult\":false,\"items\":[{\"type\":\"image\", \"image\":{\"link\":\"https://cdn1.ozone.ru/s3/multimedia-1-0/7257074868.jpg\", \"contentMode\":\"SCALE_ASPECT_FILL\"}}],\"link\":\"/product/h-gl-tsepochka-na-telo-iz-bisera-1893742906/\",\"shouldBlur\":false,\"skuId\":\"1893742906\",\"state\":[{\"type\":\"priceV2\", \"priceV2\":{\"price\":[{\"text\":\"776 ₽\", \"textStyle\":\"PRICE\"}, {\"text\":\"1 112 ₽\", \"textStyle\":\"ORIGINAL_PRICE\"}], \"discount\":\"−30%\", \"priceStyle\":{\"styleType\":\"CARD_PRICE\"}, \"preset\":\"SIZE_500\", \"paddingBottom\":\"PADDING_200\"}},{\"type\":\"textAtom\", \"textAtom\":{\"text\":\"Högl Цепочка на тело Из бисера\", \"textStyle\":\"tsBodyL\", \"maxLines\":2, \"testInfo\":{\"automatizationId\":\"tile-name\"}}, \"id\":\"name\"}],\"trackingInfo\":{\"aux_click\":{\"actionType\":\"aux_click\", \"key\":\"WPtNRZXW8hmkrJ2LTkqm3jYCB0DBZwF2Nq1klfZ0NYyN\"},\"click\":{\"actionType\":\"click\", \"key\":\"WPtNRZXW8hmkrJ2LTkqm3jYCB0DBZwF2Nq1klfZ0NYyN\"},\"right_click\":{\"actionType\":\"right_click\", \"key\":\"WPtNRZXW8hmkrJ2LTkqm3jYCB0DBZwF2Nq1klfZ0NYyN\"},\"view\":{\"actionType\":\"view\", \"key\":\"WPtNRZXW8hmkrJ2LTkqm3jYCB0DBZwF2Nq1klfZ0NYyN\"}}},{\"action\":{\"behavior\":\"BEHAVIOR_TYPE_REDIRECT\", \"link\":\"/product/kupalnik-razdelnyy-derzkaya-myata-vesenne-letnyaya-kollektsiya-2025-2189439413/?at=w0tgJkVWnuq85ZLvTWNG9OcJDj7kruXGqKQliBJ1ZNV\"},\"alt\":\"Купальник раздельный Дерзкая Мята Весенне-летняя коллекция 2025 Рекомендуем для вас\",\"isAdult\":false,\"items\":[{\"type\":\"image\", \"image\":{\"link\":\"https://cdn1.ozone.ru/s3/multimedia-1-m/7607106202.jpg\", \"contentMode\":\"SCALE_ASPECT_FILL\"}}],\"link\":\"/product/kupalnik-razdelnyy-derzkaya-myata-vesenne-letnyaya-kollektsiya-2025-2189439413/?at=w0tgJkVWnuq85ZLvTWNG9OcJDj7kruXGqKQliBJ1ZNV\",\"shouldBlur\":false,\"skuId\":\"2189439413\",\"state\":[{\"type\":\"priceV2\", \"priceV2\":{\"price\":[{\"text\":\"1 929 ₽\", \"textStyle\":\"PRICE\"}, {\"text\":\"11 990 ₽\", \"textStyle\":\"ORIGINAL_PRICE\"}], \"discount\":\"−83%\", \"priceStyle\":{\"styleType\":\"SALE_PRICE\", \"gradient\":{\"startColor\":\"#F1117E\", \"endColor\":\"#F1117E\"}}, \"preset\":\"SIZE_500\", \"paddingBottom\":\"PADDING_200\"}},{\"type\":\"textAtom\", \"textAtom\":{\"text\":\"61 шт осталось\", \"textStyle\":\"tsBodyControl400Small\", \"textColor\":\"textAccent\", \"maxLines\":1, \"testInfo\":{\"automatizationId\":\"tile-blackFridayStockbar\"}}},{\"type\":\"textAtom\", \"textAtom\":{\"text\":\"Купальник раздельный Дерзкая Мята Весенне-летняя коллекция 2025\", \"textStyle\":\"tsBodyL\", \"maxLines\":2, \"testInfo\":{\"automatizationId\":\"tile-name\"}}, \"id\":\"name\"}],\"trackingInfo\":{\"aux_click\":{\"actionType\":\"aux_click\", \"key\":\"w0tgJkVWnuq85ZLvTWNG9OcJDj7kruXGqKQliBJ1ZNV\", \"custom\":{\"advertLite\":\"AD8CSFHKPt1EFw325yW8CXy6_T9GMHtLOzFEPvJ0-Xy_htJyF54qStPl27BkCbld9OvpE-VuRvtLLse8CuM\"}},\"click\":{\"actionType\":\"click\", \"key\":\"w0tgJkVWnuq85ZLvTWNG9OcJDj7kruXGqKQliBJ1ZNV\", \"custom\":{\"advertLite\":\"AD8CSFHKPt1EFw325yW8CXy6_T9GMHtLOzFEPvJ0-Xy_htJyF54qStPl27BkCbld9OvpE-VuRvtLLse8CuM\"}},\"right_click\":{\"actionType\":\"right_click\", \"key\":\"w0tgJkVWnuq85ZLvTWNG9OcJDj7kruXGqKQliBJ1ZNV\", \"custom\":{\"advertLite\":\"AD8CSFHKPt1EFw325yW8CXy6_T9GMHtLOzFEPvJ0-Xy_htJyF54qStPl27BkCbld9OvpE-VuRvtLLse8CuM\"}},\"view\":{\"actionType\":\"view\", \"key\":\"w0tgJkVWnuq85ZLvTWNG9OcJDj7kruXGqKQliBJ1ZNV\"}}},{\"action\":{\"behavior\":\"BEHAVIOR_TYPE_REDIRECT\", \"link\":\"/product/top-black-cat-sport-activity-1620420650/?at=r2t4P7nGOc4O17D1tWW2LNESWZwL5BTQwnx3KFP6moo\"},\"alt\":\"Топ Black Cat Sport \\u0026 activity Рекомендуем для вас\",\"isAdult\":false,\"items\":[{\"type\":\"image\", \"image\":{\"link\":\"https://cdn1.ozone.ru/s3/multimedia-1-o/7688336784.jpg\", \"contentMode\":\"SCALE_ASPECT_FILL\"}}],\"link\":\"/product/top-black-cat-sport-activity-1620420650/?at=r2t4P7nGOc4O17D1tWW2LNESWZwL5BTQwnx3KFP6moo\",\"shouldBlur\":false,\"skuId\":\"1620420650\",\"state\":[{\"type\":\"priceV2\", \"priceV2\":{\"price\":[{\"text\":\"1 078 ₽\", \"textStyle\":\"PRICE\"}, {\"text\":\"6 000 ₽\", \"textStyle\":\"ORIGINAL_PRICE\"}], \"discount\":\"−82%\", \"priceStyle\":{\"styleType\":\"SALE_PRICE\", \"gradient\":{\"startColor\":\"#F1117E\", \"endColor\":\"#F1117E\"}}, \"preset\":\"SIZE_500\", \"paddingBottom\":\"PADDING_200\"}},{\"type\":\"textAtom\", \"textAtom\":{\"text\":\"70 шт осталось\", \"textStyle\":\"tsBodyControl400Small\", \"textColor\":\"textAccent\", \"maxLines\":1, \"testInfo\":{\"automatizationId\":\"tile-blackFridayStockbar\"}}},{\"type\":\"textAtom\", \"textAtom\":{\"text\":\"Топ Black Cat Sport &amp; activity\", \"textStyle\":\"tsBodyL\", \"maxLines\":2, \"testInfo\":{\"automatizationId\":\"tile-name\"}}, \"id\":\"name\"}],\"trackingInfo\":{\"aux_click\":{\"actionType\":\"aux_click\", \"key\":\"r2t4P7nGOc4O17D1tWW2LNESWZwL5BTQwnx3KFP6moo\", \"custom\":{\"advertLite\":\"AD8CI4z0h00Nk9DIdykWof46P5pZvd4jE3bW9II3oCyN5AhiUAnfVNqisdoVcrLPy9TOotkvxXrF2FYMRA\"}},\"click\":{\"actionType\":\"click\", \"key\":\"r2t4P7nGOc4O17D1tWW2LNESWZwL5BTQwnx3KFP6moo\", \"custom\":{\"advertLite\":\"AD8CI4z0h00Nk9DIdykWof46P5pZvd4jE3bW9II3oCyN5AhiUAnfVNqisdoVcrLPy9TOotkvxXrF2FYMRA\"}},\"right_click\":{\"actionType\":\"right_click\", \"key\":\"r2t4P7nGOc4O17D1tWW2LNESWZwL5BTQwnx3KFP6moo\", \"custom\":{\"advertLite\":\"AD8CI4z0h00Nk9DIdykWof46P5pZvd4jE3bW9II3oCyN5AhiUAnfVNqisdoVcrLPy9TOotkvxXrF2FYMRA\"}},\"view\":{\"actionType\":\"view\", \"key\":\"r2t4P7nGOc4O17D1tWW2LNESWZwL5BTQwnx3KFP6moo\"}}},{\"action\":{\"behavior\":\"BEHAVIOR_TYPE_REDIRECT\", \"link\":\"/product/komplekt-belya-siyay-style-2080778336/\"},\"alt\":\"Комплект белья Siyay_style Рекомендуем для вас\",\"isAdult\":false,\"items\":[{\"type\":\"image\", \"image\":{\"link\":\"https://cdn1.ozone.ru/s3/multimedia-1-l/7495495653.jpg\", \"contentMode\":\"SCALE_ASPECT_FILL\"}}],\"link\":\"/product/komplekt-belya-siyay-style-2080778336/\",\"shouldBlur\":false,\"skuId\":\"2080778336\",\"state\":[{\"type\":\"priceV2\", \"priceV2\":{\"price\":[{\"text\":\"1 387 ₽\", \"textStyle\":\"PRICE\"}, {\"text\":\"5 830 ₽\", \"textStyle\":\"ORIGINAL_PRICE\"}], \"discount\":\"−76%\", \"priceStyle\":{\"styleType\":\"SALE_PRICE\", \"gradient\":{\"startColor\":\"#F1117E\", \"endColor\":\"#F1117E\"}}, \"preset\":\"SIZE_500\", \"paddingBottom\":\"PADDING_200\"}},{\"type\":\"textAtom\", \"textAtom\":{\"text\":\"8 шт осталось\", \"textStyle\":\"tsBodyControl400Small\", \"textColor\":\"textAccent\", \"maxLines\":1, \"testInfo\":{\"automatizationId\":\"tile-blackFridayStockbar\"}}},{\"type\":\"textAtom\", \"textAtom\":{\"text\":\"Комплект белья Siyay_style\", \"textStyle\":\"tsBodyL\", \"maxLines\":2, \"testInfo\":{\"automatizationId\":\"tile-name\"}}, \"id\":\"name\"}],\"trackingInfo\":{\"aux_click\":{\"actionType\":\"aux_click\", \"key\":\"08tYqQgLzc3LJ4B3un05K62CMBYE7oCW9J10qIwnrnx1\"},\"click\":{\"actionType\":\"click\", \"key\":\"08tYqQgLzc3LJ4B3un05K62CMBYE7oCW9J10qIwnrnx1\"},\"right_click\":{\"actionType\":\"right_click\", \"key\":\"08tYqQgLzc3LJ4B3un05K62CMBYE7oCW9J10qIwnrnx1\"},\"view\":{\"actionType\":\"view\", \"key\":\"08tYqQgLzc3LJ4B3un05K62CMBYE7oCW9J10qIwnrnx1\"}}},{\"action\":{\"behavior\":\"BEHAVIOR_TYPE_REDIRECT\", \"link\":\"/product/sumka-shopper-na-plecho-a4-tout-2025938001/?at=57tw53pD1cOkBj8MS8O0gKlS14vnZWf1LgMYDtyG2pqk\"},\"alt\":\"Сумка шоппер на плечо а4 тоут Рекомендуем для вас\",\"isAdult\":false,\"items\":[{\"type\":\"image\", \"image\":{\"link\":\"https://cdn1.ozone.ru/s3/multimedia-1-1/7763993209.jpg\", \"contentMode\":\"SCALE_ASPECT_FILL\"}}],\"link\":\"/product/sumka-shopper-na-plecho-a4-tout-2025938001/?at=57tw53pD1cOkBj8MS8O0gKlS14vnZWf1LgMYDtyG2pqk\",\"shouldBlur\":false,\"skuId\":\"2025938001\",\"state\":[{\"type\":\"priceV2\", \"priceV2\":{\"price\":[{\"text\":\"1 593 ₽\", \"textStyle\":\"PRICE\"}, {\"text\":\"5 050 ₽\", \"textStyle\":\"ORIGINAL_PRICE\"}], \"discount\":\"−68%\", \"priceStyle\":{\"styleType\":\"SALE_PRICE\", \"gradient\":{\"startColor\":\"#F1117E\", \"endColor\":\"#F1117E\"}}, \"preset\":\"SIZE_500\", \"paddingBottom\":\"PADDING_200\"}},{\"type\":\"textAtom\", \"textAtom\":{\"text\":\"67 шт осталось\", \"textStyle\":\"tsBodyControl400Small\", \"textColor\":\"textAccent\", \"maxLines\":1, \"testInfo\":{\"automatizationId\":\"tile-blackFridayStockbar\"}}},{\"type\":\"textAtom\", \"textAtom\":{\"text\":\"Сумка шоппер на плечо а4 тоут\", \"textStyle\":\"tsBodyL\", \"maxLines\":2, \"testInfo\":{\"automatizationId\":\"tile-name\"}}, \"id\":\"name\"}],\"trackingInfo\":{\"aux_click\":{\"actionType\":\"aux_click\", \"key\":\"57tw53pD1cOkBj8MS8O0gKlS14vnZWf1LgMYDtyG2pqk\", \"custom\":{\"advertLite\":\"AD8CTZG3pIF7i7ME7DrY75kDGnHHLgxcGwq0K-FjXR4s3dhjuKr4c_dxrZUvMDsh4T05p4po77QY29CRrQ\"}},\"click\":{\"actionType\":\"click\", \"key\":\"57tw53pD1cOkBj8MS8O0gKlS14vnZWf1LgMYDtyG2pqk\", \"custom\":{\"advertLite\":\"AD8CTZG3pIF7i7ME7DrY75kDGnHHLgxcGwq0K-FjXR4s3dhjuKr4c_dxrZUvMDsh4T05p4po77QY29CRrQ\"}},\"right_click\":{\"actionType\":\"right_click\", \"key\":\"57tw53pD1cOkBj8MS8O0gKlS14vnZWf1LgMYDtyG2pqk\", \"custom\":{\"advertLite\":\"AD8CTZG3pIF7i7ME7DrY75kDGnHHLgxcGwq0K-FjXR4s3dhjuKr4c_dxrZUvMDsh4T05p4po77QY29CRrQ\"}},\"view\":{\"actionType\":\"view\", \"key\":\"57tw53pD1cOkBj8MS8O0gKlS14vnZWf1LgMYDtyG2pqk\"}}},{\"action\":{\"behavior\":\"BEHAVIOR_TYPE_REDIRECT\", \"link\":\"/product/lif-kupalnyy-incanto-1436266042/?at=PjtJ89NkncQLl2pZUPJlZMyC69JvK0cxR1VMYCON5G3k\"},\"alt\":\"Лиф купальный Incanto Рекомендуем для вас\",\"isAdult\":false,\"items\":[{\"type\":\"image\", \"image\":{\"link\":\"https://cdn1.ozone.ru/s3/multimedia-1-q/6932939138.jpg\", \"contentMode\":\"SCALE_ASPECT_FILL\"}}],\"link\":\"/product/lif-kupalnyy-incanto-1436266042/?at=PjtJ89NkncQLl2pZUPJlZMyC69JvK0cxR1VMYCON5G3k\",\"shouldBlur\":false,\"skuId\":\"1436266042\",\"state\":[{\"type\":\"priceV2\", \"priceV2\":{\"price\":[{\"text\":\"1 781 ₽\", \"textStyle\":\"PRICE\"}, {\"text\":\"7 899 ₽\", \"textStyle\":\"ORIGINAL_PRICE\"}], \"discount\":\"−77%\", \"priceStyle\":{\"styleType\":\"SALE_PRICE\", \"gradient\":{\"startColor\":\"#F1117E\", \"endColor\":\"#F1117E\"}}, \"preset\":\"SIZE_500\", \"paddingBottom\":\"PADDING_200\"}},{\"type\":\"textAtom\", \"textAtom\":{\"text\":\"29 шт осталось\", \"textStyle\":\"tsBodyControl400Small\", \"textColor\":\"textAccent\", \"maxLines\":1, \"testInfo\":{\"automatizationId\":\"tile-blackFridayStockbar\"}}},{\"type\":\"textAtom\", \"textAtom\":{\"text\":\"Лиф купальный Incanto\", \"textStyle\":\"tsBodyL\", \"maxLines\":2, \"testInfo\":{\"automatizationId\":\"tile-name\"}}, \"id\":\"name\"}],\"trackingInfo\":{\"aux_click\":{\"actionType\":\"aux_click\", \"key\":\"PjtJ89NkncQLl2pZUPJlZMyC69JvK0cxR1VMYCON5G3k\", \"custom\":{\"advertLite\":\"AD8C5iu13BqXxtDb6sveDgfxrBUStai9S77ejP3HhyxmBvPjkWS9R1T56xYyA-UJ6zfUC__IVvyqvyYaC2M\"}},\"click\":{\"actionType\":\"click\", \"key\":\"PjtJ89NkncQLl2pZUPJlZMyC69JvK0cxR1VMYCON5G3k\", \"custom\":{\"advertLite\":\"AD8C5iu13BqXxtDb6sveDgfxrBUStai9S77ejP3HhyxmBvPjkWS9R1T56xYyA-UJ6zfUC__IVvyqvyYaC2M\"}},\"right_click\":{\"actionType\":\"right_click\", \"key\":\"PjtJ89NkncQLl2pZUPJlZMyC69JvK0cxR1VMYCON5G3k\", \"custom\":{\"advertLite\":\"AD8C5iu13BqXxtDb6sveDgfxrBUStai9S77ejP3HhyxmBvPjkWS9R1T56xYyA-UJ6zfUC__IVvyqvyYaC2M\"}},\"view\":{\"actionType\":\"view\", \"key\":\"PjtJ89NkncQLl2pZUPJlZMyC69JvK0cxR1VMYCON5G3k\"}}},{\"action\":{\"behavior\":\"BEHAVIOR_TYPE_REDIRECT\", \"link\":\"/product/tunika-2089580600/?at=z6tOQEwAzcO7BPO3SkN1pz5SPEJrRltw6zPqVCv9Npp4\"},\"alt\":\"Туника Рекомендуем для вас\",\"isAdult\":false,\"items\":[{\"type\":\"image\", \"image\":{\"link\":\"https://cdn1.ozone.ru/s3/multimedia-1-w/7036479932.jpg\", \"contentMode\":\"SCALE_ASPECT_FILL\"}}],\"link\":\"/product/tunika-2089580600/?at=z6tOQEwAzcO7BPO3SkN1pz5SPEJrRltw6zPqVCv9Npp4\",\"shouldBlur\":false,\"skuId\":\"2089580600\",\"state\":[{\"type\":\"priceV2\", \"priceV2\":{\"price\":[{\"text\":\"970 ₽\", \"textStyle\":\"PRICE\"}, {\"text\":\"2 851 ₽\", \"textStyle\":\"ORIGINAL_PRICE\"}], \"discount\":\"−65%\", \"priceStyle\":{\"styleType\":\"SALE_PRICE\", \"gradient\":{\"startColor\":\"#F1117E\", \"endColor\":\"#F1117E\"}}, \"preset\":\"SIZE_500\", \"paddingBottom\":\"PADDING_200\"}},{\"type\":\"textAtom\", \"textAtom\":{\"text\":\"730 шт осталось\", \"textStyle\":\"tsBodyControl400Small\", \"textColor\":\"textAccent\", \"maxLines\":1, \"testInfo\":{\"automatizationId\":\"tile-blackFridayStockbar\"}}},{\"type\":\"textAtom\", \"textAtom\":{\"text\":\"Туника\", \"textStyle\":\"tsBodyL\", \"maxLines\":2, \"testInfo\":{\"automatizationId\":\"tile-name\"}}, \"id\":\"name\"}],\"trackingInfo\":{\"aux_click\":{\"actionType\":\"aux_click\", \"key\":\"z6tOQEwAzcO7BPO3SkN1pz5SPEJrRltw6zPqVCv9Npp4\", \"custom\":{\"advertLite\":\"AD8CUmKusg_2YNlaIZw9kKU8ZwBdMrwnnju5rgKQdG_RcH41rLxVENxQiGzltkkdKnMwB2UXzg-pSVFd0g\"}},\"click\":{\"actionType\":\"click\", \"key\":\"z6tOQEwAzcO7BPO3SkN1pz5SPEJrRltw6zPqVCv9Npp4\", \"custom\":{\"advertLite\":\"AD8CUmKusg_2YNlaIZw9kKU8ZwBdMrwnnju5rgKQdG_RcH41rLxVENxQiGzltkkdKnMwB2UXzg-pSVFd0g\"}},\"right_click\":{\"actionType\":\"right_click\", \"key\":\"z6tOQEwAzcO7BPO3SkN1pz5SPEJrRltw6zPqVCv9Npp4\", \"custom\":{\"advertLite\":\"AD8CUmKusg_2YNlaIZw9kKU8ZwBdMrwnnju5rgKQdG_RcH41rLxVENxQiGzltkkdKnMwB2UXzg-pSVFd0g\"}},\"view\":{\"actionType\":\"view\", \"key\":\"z6tOQEwAzcO7BPO3SkN1pz5SPEJrRltw6zPqVCv9Npp4\"}}},{\"action\":{\"behavior\":\"BEHAVIOR_TYPE_REDIRECT\", \"link\":\"/product/komplekt-trusov-slipy-brify-3-sht-1953899279/?at=A6tGLBlz5c1GE0kGfJoOQ3ncPNGqK5hDAr74YhPnz2Rm\"},\"alt\":\"Комплект трусов слипы, брифы, 3 шт Рекомендуем для вас\",\"isAdult\":false,\"items\":[{\"type\":\"image\", \"image\":{\"link\":\"https://cdn1.ozone.ru/s3/multimedia-1-h/7400451077.jpg\", \"contentMode\":\"SCALE_ASPECT_FILL\"}}],\"link\":\"/product/komplekt-trusov-slipy-brify-3-sht-1953899279/?at=A6tGLBlz5c1GE0kGfJoOQ3ncPNGqK5hDAr74YhPnz2Rm\",\"shouldBlur\":false,\"skuId\":\"1953899279\",\"state\":[{\"type\":\"priceV2\", \"priceV2\":{\"price\":[{\"text\":\"687 ₽\", \"textStyle\":\"PRICE\"}, {\"text\":\"1 994 ₽\", \"textStyle\":\"ORIGINAL_PRICE\"}], \"discount\":\"−65%\", \"priceStyle\":{\"styleType\":\"CARD_PRICE\"}, \"preset\":\"SIZE_500\", \"paddingBottom\":\"PADDING_200\"}},{\"type\":\"textAtom\", \"textAtom\":{\"text\":\"Комплект трусов слипы, брифы, 3 шт\", \"textStyle\":\"tsBodyL\", \"maxLines\":2, \"testInfo\":{\"automatizationId\":\"tile-name\"}}, \"id\":\"name\"}],\"trackingInfo\":{\"aux_click\":{\"actionType\":\"aux_click\", \"key\":\"A6tGLBlz5c1GE0kGfJoOQ3ncPNGqK5hDAr74YhPnz2Rm\", \"custom\":{\"advertLite\":\"AD8CLmcAQDkETGG_WXuZFbe99wIhVDfHtIUoDzTx8gQmVymQDjg4irQrO7uA9dzEE6rsn14MUwp5lbL3lw\"}},\"click\":{\"actionType\":\"click\", \"key\":\"A6tGLBlz5c1GE0kGfJoOQ3ncPNGqK5hDAr74YhPnz2Rm\", \"custom\":{\"advertLite\":\"AD8CLmcAQDkETGG_WXuZFbe99wIhVDfHtIUoDzTx8gQmVymQDjg4irQrO7uA9dzEE6rsn14MUwp5lbL3lw\"}},\"right_click\":{\"actionType\":\"right_click\", \"key\":\"A6tGLBlz5c1GE0kGfJoOQ3ncPNGqK5hDAr74YhPnz2Rm\", \"custom\":{\"advertLite\":\"AD8CLmcAQDkETGG_WXuZFbe99wIhVDfHtIUoDzTx8gQmVymQDjg4irQrO7uA9dzEE6rsn14MUwp5lbL3lw\"}},\"view\":{\"actionType\":\"view\", \"key\":\"A6tGLBlz5c1GE0kGfJoOQ3ncPNGqK5hDAr74YhPnz2Rm\"}}},{\"action\":{\"behavior\":\"BEHAVIOR_TYPE_REDIRECT\", \"link\":\"/product/trusy-stringi-alisia-grace-4-sht-1717232399/?at=46tRME9vxU4jRx5S5KvDDriwAyrWh3Mgx4KF84OPDN\"},\"alt\":\"Трусы стринги Alisia GRACE, 4 шт Рекомендуем для вас\",\"isAdult\":false,\"items\":[{\"type\":\"image\", \"image\":{\"link\":\"https://cdn1.ozone.ru/s3/multimedia-1-z/7650581867.jpg\", \"contentMode\":\"SCALE_ASPECT_FILL\"}}],\"link\":\"/product/trusy-stringi-alisia-grace-4-sht-1717232399/?at=46tRME9vxU4jRx5S5KvDDriwAyrWh3Mgx4KF84OPDN\",\"shouldBlur\":false,\"skuId\":\"1717232399\",\"state\":[{\"type\":\"priceV2\", \"priceV2\":{\"price\":[{\"text\":\"439 ₽\", \"textStyle\":\"PRICE\"}, {\"text\":\"1 004 ₽\", \"textStyle\":\"ORIGINAL_PRICE\"}], \"discount\":\"−56%\", \"priceStyle\":{\"styleType\":\"SALE_PRICE\", \"gradient\":{\"startColor\":\"#F1117E\", \"endColor\":\"#F1117E\"}}, \"preset\":\"SIZE_500\", \"paddingBottom\":\"PADDING_200\"}},{\"type\":\"textAtom\", \"textAtom\":{\"text\":\"20 шт осталось\", \"textStyle\":\"tsBodyControl400Small\", \"textColor\":\"textAccent\", \"maxLines\":1, \"testInfo\":{\"automatizationId\":\"tile-blackFridayStockbar\"}}},{\"type\":\"textAtom\", \"textAtom\":{\"text\":\"Трусы стринги Alisia GRACE, 4 шт\", \"textStyle\":\"tsBodyL\", \"maxLines\":2, \"testInfo\":{\"automatizationId\":\"tile-name\"}}, \"id\":\"name\"}],\"trackingInfo\":{\"aux_click\":{\"actionType\":\"aux_click\", \"key\":\"46tRME9vxU4jRx5S5KvDDriwAyrWh3Mgx4KF84OPDN\", \"custom\":{\"advertLite\":\"AD8Cq7palcQJ2h_PQr2mRcIWOFt8bokWAvZMeo1--Px3kPbkJZRkY4a4Lcf7iZX9kjtxQRdLz3amvJ7Ypw\"}},\"click\":{\"actionType\":\"click\", \"key\":\"46tRME9vxU4jRx5S5KvDDriwAyrWh3Mgx4KF84OPDN\", \"custom\":{\"advertLite\":\"AD8Cq7palcQJ2h_PQr2mRcIWOFt8bokWAvZMeo1--Px3kPbkJZRkY4a4Lcf7iZX9kjtxQRdLz3amvJ7Ypw\"}},\"right_click\":{\"actionType\":\"right_click\", \"key\":\"46tRME9vxU4jRx5S5KvDDriwAyrWh3Mgx4KF84OPDN\", \"custom\":{\"advertLite\":\"AD8Cq7palcQJ2h_PQr2mRcIWOFt8bokWAvZMeo1--Px3kPbkJZRkY4a4Lcf7iZX9kjtxQRdLz3amvJ7Ypw\"}},\"view\":{\"actionType\":\"view\", \"key\":\"46tRME9vxU4jRx5S5KvDDriwAyrWh3Mgx4KF84OPDN\"}}},{\"action\":{\"behavior\":\"BEHAVIOR_TYPE_REDIRECT\", \"link\":\"/product/kupalnik-razdelnyy-love-skin-s-tsvetkom-1567508823/\"},\"alt\":\"Купальник раздельный Love Skin с цветком Рекомендуем для вас\",\"isAdult\":false,\"items\":[{\"type\":\"image\", \"image\":{\"link\":\"https://cdn1.ozone.ru/s3/multimedia-1-5/6938568005.jpg\", \"contentMode\":\"SCALE_ASPECT_FILL\"}}],\"link\":\"/product/kupalnik-razdelnyy-love-skin-s-tsvetkom-1567508823/\",\"shouldBlur\":false,\"skuId\":\"1567508823\",\"state\":[{\"type\":\"priceV2\", \"priceV2\":{\"price\":[{\"text\":\"1 294 ₽\", \"textStyle\":\"PRICE\"}, {\"text\":\"7 931 ₽\", \"textStyle\":\"ORIGINAL_PRICE\"}], \"discount\":\"−83%\", \"priceStyle\":{\"styleType\":\"SALE_PRICE\", \"gradient\":{\"startColor\":\"#F1117E\", \"endColor\":\"#F1117E\"}}, \"preset\":\"SIZE_500\", \"paddingBottom\":\"PADDING_200\"}},{\"type\":\"textAtom\", \"textAtom\":{\"text\":\"21 шт осталось\", \"textStyle\":\"tsBodyControl400Small\", \"textColor\":\"textAccent\", \"maxLines\":1, \"testInfo\":{\"automatizationId\":\"tile-blackFridayStockbar\"}}},{\"type\":\"textAtom\", \"textAtom\":{\"text\":\"Купальник раздельный Love Skin с цветком\", \"textStyle\":\"tsBodyL\", \"maxLines\":2, \"testInfo\":{\"automatizationId\":\"tile-name\"}}, \"id\":\"name\"}],\"trackingInfo\":{\"aux_click\":{\"actionType\":\"aux_click\", \"key\":\"Rltyjo0zXIL9E1mqSzKWggPF9r9E4AcnykBLLHjwYDLw\"},\"click\":{\"actionType\":\"click\", \"key\":\"Rltyjo0zXIL9E1mqSzKWggPF9r9E4AcnykBLLHjwYDLw\"},\"right_click\":{\"actionType\":\"right_click\", \"key\":\"Rltyjo0zXIL9E1mqSzKWggPF9r9E4AcnykBLLHjwYDLw\"},\"view\":{\"actionType\":\"view\", \"key\":\"Rltyjo0zXIL9E1mqSzKWggPF9r9E4AcnykBLLHjwYDLw\"}}},{\"action\":{\"behavior\":\"BEHAVIOR_TYPE_REDIRECT\", \"link\":\"/product/plavki-shorty-1-sht-2023219020/?at=Brtzp0RONhQRM1Onhy5wnVJh51RAYLsRQorPOIL1zRAP\"},\"alt\":\"Плавки шорты, 1 шт Рекомендуем для вас\",\"isAdult\":false,\"items\":[{\"type\":\"image\", \"image\":{\"link\":\"https://cdn1.ozone.ru/s3/multimedia-1-h/7460628713.jpg\", \"contentMode\":\"SCALE_ASPECT_FILL\"}}],\"link\":\"/product/plavki-shorty-1-sht-2023219020/?at=Brtzp0RONhQRM1Onhy5wnVJh51RAYLsRQorPOIL1zRAP\",\"shouldBlur\":false,\"skuId\":\"2023219020\",\"state\":[{\"type\":\"priceV2\", \"priceV2\":{\"price\":[{\"text\":\"1 422 ₽\", \"textStyle\":\"PRICE\"}, {\"text\":\"1 978 ₽\", \"textStyle\":\"ORIGINAL_PRICE\"}], \"discount\":\"−28%\", \"priceStyle\":{\"styleType\":\"CARD_PRICE\"}, \"preset\":\"SIZE_500\", \"paddingBottom\":\"PADDING_200\"}},{\"type\":\"textAtom\", \"textAtom\":{\"text\":\"Плавки шорты, 1 шт\", \"textStyle\":\"tsBodyL\", \"maxLines\":2, \"testInfo\":{\"automatizationId\":\"tile-name\"}}, \"id\":\"name\"}],\"trackingInfo\":{\"aux_click\":{\"actionType\":\"aux_click\", \"key\":\"Brtzp0RONhQRM1Onhy5wnVJh51RAYLsRQorPOIL1zRAP\", \"custom\":{\"advertLite\":\"AD8C56AoTOTM31svqUzOCSmZrFKWljGd73K1O4rT6VVrKBprOftcu-w9ubecBArgaBe5mKrzyEMzc1uW_Is\"}},\"click\":{\"actionType\":\"click\", \"key\":\"Brtzp0RONhQRM1Onhy5wnVJh51RAYLsRQorPOIL1zRAP\", \"custom\":{\"advertLite\":\"AD8C56AoTOTM31svqUzOCSmZrFKWljGd73K1O4rT6VVrKBprOftcu-w9ubecBArgaBe5mKrzyEMzc1uW_Is\"}},\"right_click\":{\"actionType\":\"right_click\", \"key\":\"Brtzp0RONhQRM1Onhy5wnVJh51RAYLsRQorPOIL1zRAP\", \"custom\":{\"advertLite\":\"AD8C56AoTOTM31svqUzOCSmZrFKWljGd73K1O4rT6VVrKBprOftcu-w9ubecBArgaBe5mKrzyEMzc1uW_Is\"}},\"view\":{\"actionType\":\"view\", \"key\":\"Brtzp0RONhQRM1Onhy5wnVJh51RAYLsRQorPOIL1zRAP\"}}},{\"action\":{\"behavior\":\"BEHAVIOR_TYPE_REDIRECT\", \"link\":\"/product/komplekt-trusov-boksery-bokai-trusy-muzhskie-boksery-4-sht-617476718/?at=vQtrpqL3ZfjlxMWGCN2rNEPt08mJ5rS8q5jknSzjEQgN\"},\"alt\":\"Комплект трусов боксеры Bokai трусы мужские боксеры, 4 шт Рекомендуем для вас\",\"isAdult\":false,\"items\":[{\"type\":\"image\", \"image\":{\"link\":\"https://cdn1.ozone.ru/s3/multimedia-b/6853012319.jpg\", \"contentMode\":\"SCALE_ASPECT_FILL\"}}],\"link\":\"/product/komplekt-trusov-boksery-bokai-trusy-muzhskie-boksery-4-sht-617476718/?at=vQtrpqL3ZfjlxMWGCN2rNEPt08mJ5rS8q5jknSzjEQgN\",\"shouldBlur\":false,\"skuId\":\"617476718\",\"state\":[{\"type\":\"priceV2\", \"priceV2\":{\"price\":[{\"text\":\"724 ₽\", \"textStyle\":\"PRICE\"}, {\"text\":\"2 594 ₽\", \"textStyle\":\"ORIGINAL_PRICE\"}], \"discount\":\"−72%\", \"priceStyle\":{\"styleType\":\"CARD_PRICE\"}, \"preset\":\"SIZE_500\", \"paddingBottom\":\"PADDING_200\"}},{\"type\":\"textAtom\", \"textAtom\":{\"text\":\"Комплект трусов боксеры Bokai трусы мужские боксеры, 4 шт\", \"textStyle\":\"tsBodyL\", \"maxLines\":2, \"testInfo\":{\"automatizationId\":\"tile-name\"}}, \"id\":\"name\"}],\"trackingInfo\":{\"aux_click\":{\"actionType\":\"aux_click\", \"key\":\"vQtrpqL3ZfjlxMWGCN2rNEPt08mJ5rS8q5jknSzjEQgN\", \"custom\":{\"advertLite\":\"AD8CdwhSiCYiqrc7v8sTtxaJzLo1iUBRmV8I9L9qvrWjDE9xigqNReDE7HtQY-8kOC0qjYFwS8_UpbToKRc\"}},\"click\":{\"actionType\":\"click\", \"key\":\"vQtrpqL3ZfjlxMWGCN2rNEPt08mJ5rS8q5jknSzjEQgN\", \"custom\":{\"advertLite\":\"AD8CdwhSiCYiqrc7v8sTtxaJzLo1iUBRmV8I9L9qvrWjDE9xigqNReDE7HtQY-8kOC0qjYFwS8_UpbToKRc\"}},\"right_click\":{\"actionType\":\"right_click\", \"key\":\"vQtrpqL3ZfjlxMWGCN2rNEPt08mJ5rS8q5jknSzjEQgN\", \"custom\":{\"advertLite\":\"AD8CdwhSiCYiqrc7v8sTtxaJzLo1iUBRmV8I9L9qvrWjDE9xigqNReDE7HtQY-8kOC0qjYFwS8_UpbToKRc\"}},\"view\":{\"actionType\":\"view\", \"key\":\"vQtrpqL3ZfjlxMWGCN2rNEPt08mJ5rS8q5jknSzjEQgN\"}}},{\"action\":{\"behavior\":\"BEHAVIOR_TYPE_REDIRECT\", \"link\":\"/product/plate-joli-brand-leto-2011902949/?at=99trLANpjfnq942OhAym3M0S484zxXHQKp41yuNVn7DM\"},\"alt\":\"Платье Joli BRAND Лето Рекомендуем для вас\",\"isAdult\":false,\"items\":[{\"type\":\"image\", \"image\":{\"link\":\"https://cdn1.ozone.ru/s3/multimedia-1-i/7448995134.jpg\", \"contentMode\":\"SCALE_ASPECT_FILL\"}}],\"link\":\"/product/plate-joli-brand-leto-2011902949/?at=99trLANpjfnq942OhAym3M0S484zxXHQKp41yuNVn7DM\",\"shouldBlur\":false,\"skuId\":\"2011902949\",\"state\":[{\"type\":\"priceV2\", \"priceV2\":{\"price\":[{\"text\":\"1 486 ₽\", \"textStyle\":\"PRICE\"}, {\"text\":\"4 224 ₽\", \"textStyle\":\"ORIGINAL_PRICE\"}], \"discount\":\"−64%\", \"priceStyle\":{\"styleType\":\"SALE_PRICE\", \"gradient\":{\"startColor\":\"#F1117E\", \"endColor\":\"#F1117E\"}}, \"preset\":\"SIZE_500\", \"paddingBottom\":\"PADDING_200\"}},{\"type\":\"textAtom\", \"textAtom\":{\"text\":\"985 шт осталось\", \"textStyle\":\"tsBodyControl400Small\", \"textColor\":\"textAccent\", \"maxLines\":1, \"testInfo\":{\"automatizationId\":\"tile-blackFridayStockbar\"}}},{\"type\":\"textAtom\", \"textAtom\":{\"text\":\"Платье Joli BRAND Лето\", \"textStyle\":\"tsBodyL\", \"maxLines\":2, \"testInfo\":{\"automatizationId\":\"tile-name\"}}, \"id\":\"name\"}],\"trackingInfo\":{\"aux_click\":{\"actionType\":\"aux_click\", \"key\":\"99trLANpjfnq942OhAym3M0S484zxXHQKp41yuNVn7DM\", \"custom\":{\"advertLite\":\"AD8CPx-ilrLVRGzYI3-PbP4dxjJpw2lIeJz3QPLy-Ub1C4bITO5uOQuySHsM-zYflp-UkohJ_0q5crGJFg\"}},\"click\":{\"actionType\":\"click\", \"key\":\"99trLANpjfnq942OhAym3M0S484zxXHQKp41yuNVn7DM\", \"custom\":{\"advertLite\":\"AD8CPx-ilrLVRGzYI3-PbP4dxjJpw2lIeJz3QPLy-Ub1C4bITO5uOQuySHsM-zYflp-UkohJ_0q5crGJFg\"}},\"right_click\":{\"actionType\":\"right_click\", \"key\":\"99trLANpjfnq942OhAym3M0S484zxXHQKp41yuNVn7DM\", \"custom\":{\"advertLite\":\"AD8CPx-ilrLVRGzYI3-PbP4dxjJpw2lIeJz3QPLy-Ub1C4bITO5uOQuySHsM-zYflp-UkohJ_0q5crGJFg\"}},\"view\":{\"actionType\":\"view\", \"key\":\"99trLANpjfnq942OhAym3M0S484zxXHQKp41yuNVn7DM\"}}},{\"action\":{\"behavior\":\"BEHAVIOR_TYPE_REDIRECT\", \"link\":\"/product/dobro-sumka-na-plecho-messendzher-729257521/?at=GRt2KEOQ9Fjm36YGS7qL75wUWApOrWTYJzVyYin9owrN\"},\"alt\":\"Dobro Сумка на плечо мессенджер Рекомендуем для вас\",\"isAdult\":false,\"items\":[{\"type\":\"image\", \"image\":{\"link\":\"https://cdn1.ozone.ru/s3/multimedia-y/6423432106.jpg\", \"contentMode\":\"SCALE_ASPECT_FILL\"}}],\"link\":\"/product/dobro-sumka-na-plecho-messendzher-729257521/?at=GRt2KEOQ9Fjm36YGS7qL75wUWApOrWTYJzVyYin9owrN\",\"shouldBlur\":false,\"skuId\":\"729257521\",\"state\":[{\"type\":\"priceV2\", \"priceV2\":{\"price\":[{\"text\":\"840 ₽\", \"textStyle\":\"PRICE\"}, {\"text\":\"1 970 ₽\", \"textStyle\":\"ORIGINAL_PRICE\"}], \"discount\":\"−57%\", \"priceStyle\":{\"styleType\":\"SALE_PRICE\", \"gradient\":{\"startColor\":\"#F1117E\", \"endColor\":\"#F1117E\"}}, \"preset\":\"SIZE_500\", \"paddingBottom\":\"PADDING_200\"}},{\"type\":\"textAtom\", \"textAtom\":{\"text\":\"264 шт осталось\", \"textStyle\":\"tsBodyControl400Small\", \"textColor\":\"textAccent\", \"maxLines\":1, \"testInfo\":{\"automatizationId\":\"tile-blackFridayStockbar\"}}},{\"type\":\"textAtom\", \"textAtom\":{\"text\":\"Dobro Сумка на плечо мессенджер\", \"textStyle\":\"tsBodyL\", \"maxLines\":2, \"testInfo\":{\"automatizationId\":\"tile-name\"}}, \"id\":\"name\"}],\"trackingInfo\":{\"aux_click\":{\"actionType\":\"aux_click\", \"key\":\"GRt2KEOQ9Fjm36YGS7qL75wUWApOrWTYJzVyYin9owrN\", \"custom\":{\"advertLite\":\"AD8CE-g6QB2zJ329fTRrhDcX2hAAxWau16FkYUuSgLl3uAruZN3wtInrnCzoXTFHFYNh7XTCNYNtHpQFqw\"}},\"click\":{\"actionType\":\"click\", \"key\":\"GRt2KEOQ9Fjm36YGS7qL75wUWApOrWTYJzVyYin9owrN\", \"custom\":{\"advertLite\":\"AD8CE-g6QB2zJ329fTRrhDcX2hAAxWau16FkYUuSgLl3uAruZN3wtInrnCzoXTFHFYNh7XTCNYNtHpQFqw\"}},\"right_click\":{\"actionType\":\"right_click\", \"key\":\"GRt2KEOQ9Fjm36YGS7qL75wUWApOrWTYJzVyYin9owrN\", \"custom\":{\"advertLite\":\"AD8CE-g6QB2zJ329fTRrhDcX2hAAxWau16FkYUuSgLl3uAruZN3wtInrnCzoXTFHFYNh7XTCNYNtHpQFqw\"}},\"view\":{\"actionType\":\"view\", \"key\":\"GRt2KEOQ9Fjm36YGS7qL75wUWApOrWTYJzVyYin9owrN\"}}},{\"action\":{\"behavior\":\"BEHAVIOR_TYPE_REDIRECT\", \"link\":\"/product/kupalnik-razdelnyy-womcloz-1483153124/?at=Brtzp0RONhzD3X4xIpGRkppCPMWEBESDwoOjYC87v9Rr\"},\"alt\":\"Купальник раздельный WOMCLOZ Рекомендуем для вас\",\"isAdult\":false,\"items\":[{\"type\":\"image\", \"image\":{\"link\":\"https://cdn1.ozone.ru/s3/multimedia-1-y/7637349490.jpg\", \"contentMode\":\"SCALE_ASPECT_FILL\"}}],\"link\":\"/product/kupalnik-razdelnyy-womcloz-1483153124/?at=Brtzp0RONhzD3X4xIpGRkppCPMWEBESDwoOjYC87v9Rr\",\"shouldBlur\":false,\"skuId\":\"1483153124\",\"state\":[{\"type\":\"priceV2\", \"priceV2\":{\"price\":[{\"text\":\"735 ₽\", \"textStyle\":\"PRICE\"}, {\"text\":\"5 900 ₽\", \"textStyle\":\"ORIGINAL_PRICE\"}], \"discount\":\"−87%\", \"priceStyle\":{\"styleType\":\"CARD_PRICE\"}, \"preset\":\"SIZE_500\", \"paddingBottom\":\"PADDING_200\"}},{\"type\":\"textAtom\", \"textAtom\":{\"text\":\"Купальник раздельный WOMCLOZ\", \"textStyle\":\"tsBodyL\", \"maxLines\":2, \"testInfo\":{\"automatizationId\":\"tile-name\"}}, \"id\":\"name\"}],\"trackingInfo\":{\"aux_click\":{\"actionType\":\"aux_click\", \"key\":\"Brtzp0RONhzD3X4xIpGRkppCPMWEBESDwoOjYC87v9Rr\", \"custom\":{\"advertLite\":\"AD8CiOrgbJC0zJrWIwTHANP1MtmvXAYzejn8qpGMOq1bBNIJWdl-10Z4VzIK95FZmp_NPLpr1cZZTBUOdw\"}},\"click\":{\"actionType\":\"click\", \"key\":\"Brtzp0RONhzD3X4xIpGRkppCPMWEBESDwoOjYC87v9Rr\", \"custom\":{\"advertLite\":\"AD8CiOrgbJC0zJrWIwTHANP1MtmvXAYzejn8qpGMOq1bBNIJWdl-10Z4VzIK95FZmp_NPLpr1cZZTBUOdw\"}},\"right_click\":{\"actionType\":\"right_click\", \"key\":\"Brtzp0RONhzD3X4xIpGRkppCPMWEBESDwoOjYC87v9Rr\", \"custom\":{\"advertLite\":\"AD8CiOrgbJC0zJrWIwTHANP1MtmvXAYzejn8qpGMOq1bBNIJWdl-10Z4VzIK95FZmp_NPLpr1cZZTBUOdw\"}},\"view\":{\"actionType\":\"view\", \"key\":\"Brtzp0RONhzD3X4xIpGRkppCPMWEBESDwoOjYC87v9Rr\"}}},{\"action\":{\"behavior\":\"BEHAVIOR_TYPE_REDIRECT\", \"link\":\"/product/komplekt-belya-radian-2143483957/\"},\"alt\":\"Комплект белья Radian Рекомендуем для вас\",\"isAdult\":false,\"items\":[{\"type\":\"image\", \"image\":{\"link\":\"https://cdn1.ozone.ru/s3/multimedia-1-t/7582212893.jpg\", \"contentMode\":\"SCALE_ASPECT_FILL\"}}],\"link\":\"/product/komplekt-belya-radian-2143483957/\",\"shouldBlur\":false,\"skuId\":\"2143483957\",\"state\":[{\"type\":\"priceV2\", \"priceV2\":{\"price\":[{\"text\":\"909 ₽\", \"textStyle\":\"PRICE\"}, {\"text\":\"4 500 ₽\", \"textStyle\":\"ORIGINAL_PRICE\"}], \"discount\":\"−79%\", \"priceStyle\":{\"styleType\":\"SALE_PRICE\", \"gradient\":{\"startColor\":\"#F1117E\", \"endColor\":\"#F1117E\"}}, \"preset\":\"SIZE_500\", \"paddingBottom\":\"PADDING_200\"}},{\"type\":\"textAtom\", \"textAtom\":{\"text\":\"147 шт осталось\", \"textStyle\":\"tsBodyControl400Small\", \"textColor\":\"textAccent\", \"maxLines\":1, \"testInfo\":{\"automatizationId\":\"tile-blackFridayStockbar\"}}},{\"type\":\"textAtom\", \"textAtom\":{\"text\":\"Комплект белья Radian\", \"textStyle\":\"tsBodyL\", \"maxLines\":2, \"testInfo\":{\"automatizationId\":\"tile-name\"}}, \"id\":\"name\"}],\"trackingInfo\":{\"aux_click\":{\"actionType\":\"aux_click\", \"key\":\"r2t4P7nGOc6QggwTjyPXAi8n4wPgh3ojJkpsDE6QRk\"},\"click\":{\"actionType\":\"click\", \"key\":\"r2t4P7nGOc6QggwTjyPXAi8n4wPgh3ojJkpsDE6QRk\"},\"right_click\":{\"actionType\":\"right_click\", \"key\":\"r2t4P7nGOc6QggwTjyPXAi8n4wPgh3ojJkpsDE6QRk\"},\"view\":{\"actionType\":\"view\", \"key\":\"r2t4P7nGOc6QggwTjyPXAi8n4wPgh3ojJkpsDE6QRk\"}}},{\"action\":{\"behavior\":\"BEHAVIOR_TYPE_REDIRECT\", \"link\":\"/product/leginsy-l-ombramia-1626148255/?at=z6tOQEwAzcxWRVoYFJ4zYg2HWOnA4rUg8Qj05t3rKyW5\"},\"alt\":\"Легинсы L'OMBRAMIA Рекомендуем для вас\",\"isAdult\":false,\"items\":[{\"type\":\"image\", \"image\":{\"link\":\"https://cdn1.ozone.ru/s3/multimedia-1-9/7076154285.jpg\", \"contentMode\":\"SCALE_ASPECT_FILL\"}}],\"link\":\"/product/leginsy-l-ombramia-1626148255/?at=z6tOQEwAzcxWRVoYFJ4zYg2HWOnA4rUg8Qj05t3rKyW5\",\"shouldBlur\":false,\"skuId\":\"1626148255\",\"state\":[{\"type\":\"priceV2\", \"priceV2\":{\"price\":[{\"text\":\"2 134 ₽\", \"textStyle\":\"PRICE\"}, {\"text\":\"5 399 ₽\", \"textStyle\":\"ORIGINAL_PRICE\"}], \"discount\":\"−60%\", \"priceStyle\":{\"styleType\":\"SALE_PRICE\", \"gradient\":{\"startColor\":\"#F1117E\", \"endColor\":\"#F1117E\"}}, \"preset\":\"SIZE_500\", \"paddingBottom\":\"PADDING_200\"}},{\"type\":\"textAtom\", \"textAtom\":{\"text\":\"67 шт осталось\", \"textStyle\":\"tsBodyControl400Small\", \"textColor\":\"textAccent\", \"maxLines\":1, \"testInfo\":{\"automatizationId\":\"tile-blackFridayStockbar\"}}},{\"type\":\"textAtom\", \"textAtom\":{\"text\":\"Легинсы L&#39;OMBRAMIA\", \"textStyle\":\"tsBodyL\", \"maxLines\":2, \"testInfo\":{\"automatizationId\":\"tile-name\"}}, \"id\":\"name\"}],\"trackingInfo\":{\"aux_click\":{\"actionType\":\"aux_click\", \"key\":\"z6tOQEwAzcxWRVoYFJ4zYg2HWOnA4rUg8Qj05t3rKyW5\", \"custom\":{\"advertLite\":\"AD8CFd5WMroHyA01RzYi_SmCxKuQay23lqdPtG_wPqfL7wV7AMb5F1MwjmfZ-WvilBDX0fVqZuGkzXwh5A0\"}},\"click\":{\"actionType\":\"click\", \"key\":\"z6tOQEwAzcxWRVoYFJ4zYg2HWOnA4rUg8Qj05t3rKyW5\", \"custom\":{\"advertLite\":\"AD8CFd5WMroHyA01RzYi_SmCxKuQay23lqdPtG_wPqfL7wV7AMb5F1MwjmfZ-WvilBDX0fVqZuGkzXwh5A0\"}},\"right_click\":{\"actionType\":\"right_click\", \"key\":\"z6tOQEwAzcxWRVoYFJ4zYg2HWOnA4rUg8Qj05t3rKyW5\", \"custom\":{\"advertLite\":\"AD8CFd5WMroHyA01RzYi_SmCxKuQay23lqdPtG_wPqfL7wV7AMb5F1MwjmfZ-WvilBDX0fVqZuGkzXwh5A0\"}},\"view\":{\"actionType\":\"view\", \"key\":\"z6tOQEwAzcxWRVoYFJ4zYg2HWOnA4rUg8Qj05t3rKyW5\"}}},{\"action\":{\"behavior\":\"BEHAVIOR_TYPE_REDIRECT\", \"link\":\"/product/futbolka-2012713097/?at=PjtJ89Nknc1qkmrkto2vA4ncDpBgNrfMrOz41CK09KzE\"},\"alt\":\"Футболка Рекомендуем для вас\",\"isAdult\":false,\"items\":[{\"type\":\"image\", \"image\":{\"link\":\"https://cdn1.ozone.ru/s3/multimedia-1-6/7451833362.jpg\", \"contentMode\":\"SCALE_ASPECT_FILL\"}}],\"link\":\"/product/futbolka-2012713097/?at=PjtJ89Nknc1qkmrkto2vA4ncDpBgNrfMrOz41CK09KzE\",\"shouldBlur\":false,\"skuId\":\"2012713097\",\"state\":[{\"type\":\"priceV2\", \"priceV2\":{\"price\":[{\"text\":\"411 ₽\", \"textStyle\":\"PRICE\"}, {\"text\":\"1 446 ₽\", \"textStyle\":\"ORIGINAL_PRICE\"}], \"discount\":\"−71%\", \"priceStyle\":{\"styleType\":\"SALE_PRICE\", \"gradient\":{\"startColor\":\"#F1117E\", \"endColor\":\"#F1117E\"}}, \"preset\":\"SIZE_500\", \"paddingBottom\":\"PADDING_200\"}},{\"type\":\"textAtom\", \"textAtom\":{\"text\":\"3 875 шт осталось\", \"textStyle\":\"tsBodyControl400Small\", \"textColor\":\"textAccent\", \"maxLines\":1, \"testInfo\":{\"automatizationId\":\"tile-blackFridayStockbar\"}}},{\"type\":\"textAtom\", \"textAtom\":{\"text\":\"Футболка\", \"textStyle\":\"tsBodyL\", \"maxLines\":2, \"testInfo\":{\"automatizationId\":\"tile-name\"}}, \"id\":\"name\"}],\"trackingInfo\":{\"aux_click\":{\"actionType\":\"aux_click\", \"key\":\"PjtJ89Nknc1qkmrkto2vA4ncDpBgNrfMrOz41CK09KzE\", \"custom\":{\"advertLite\":\"AD8CB6m7NzLqSymo_8IzIQLFxbcIkutlSGqqZ9O5BoanIRB2goLkfqsoZyLDLJUxzhay9S7u-tWB93HRBw\"}},\"click\":{\"actionType\":\"click\", \"key\":\"PjtJ89Nknc1qkmrkto2vA4ncDpBgNrfMrOz41CK09KzE\", \"custom\":{\"advertLite\":\"AD8CB6m7NzLqSymo_8IzIQLFxbcIkutlSGqqZ9O5BoanIRB2goLkfqsoZyLDLJUxzhay9S7u-tWB93HRBw\"}},\"right_click\":{\"actionType\":\"right_click\", \"key\":\"PjtJ89Nknc1qkmrkto2vA4ncDpBgNrfMrOz41CK09KzE\", \"custom\":{\"advertLite\":\"AD8CB6m7NzLqSymo_8IzIQLFxbcIkutlSGqqZ9O5BoanIRB2goLkfqsoZyLDLJUxzhay9S7u-tWB93HRBw\"}},\"view\":{\"actionType\":\"view\", \"key\":\"PjtJ89Nknc1qkmrkto2vA4ncDpBgNrfMrOz41CK09KzE\"}}},{\"action\":{\"behavior\":\"BEHAVIOR_TYPE_REDIRECT\", \"link\":\"/product/trusy-brazilyana-stringi-arushanoff-nizhnee-bele-4-sht-1259593928/?at=VvtzNmkR8hrG8AzvTOGz4BRf0o30wKCEloxPgfvLElj1\"},\"alt\":\"Трусы бразильяна, стринги ARUSHANOFF Нижнее белье, 4 шт Рекомендуем для вас\",\"isAdult\":false,\"items\":[{\"type\":\"image\", \"image\":{\"link\":\"https://cdn1.ozone.ru/s3/multimedia-1-k/7750381016.jpg\", \"contentMode\":\"SCALE_ASPECT_FILL\"}}],\"link\":\"/product/trusy-brazilyana-stringi-arushanoff-nizhnee-bele-4-sht-1259593928/?at=VvtzNmkR8hrG8AzvTOGz4BRf0o30wKCEloxPgfvLElj1\",\"shouldBlur\":false,\"skuId\":\"1259593928\",\"state\":[{\"type\":\"priceV2\", \"priceV2\":{\"price\":[{\"text\":\"828 ₽\", \"textStyle\":\"PRICE\"}, {\"text\":\"2 990 ₽\", \"textStyle\":\"ORIGINAL_PRICE\"}], \"discount\":\"−72%\", \"priceStyle\":{\"styleType\":\"CARD_PRICE\"}, \"preset\":\"SIZE_500\", \"paddingBottom\":\"PADDING_200\"}},{\"type\":\"textAtom\", \"textAtom\":{\"text\":\"Трусы бразильяна, стринги ARUSHANOFF Нижнее белье, 4 шт\", \"textStyle\":\"tsBodyL\", \"maxLines\":2, \"testInfo\":{\"automatizationId\":\"tile-name\"}}, \"id\":\"name\"}],\"trackingInfo\":{\"aux_click\":{\"actionType\":\"aux_click\", \"key\":\"VvtzNmkR8hrG8AzvTOGz4BRf0o30wKCEloxPgfvLElj1\", \"custom\":{\"advertLite\":\"AD8CNMKJdH8z_TI6OK3gt22QHTS4dWYqqC1DuhGiclvncnCh-WnNUljZbvGkFOnYNiNx4lO0NmA7Pz7jsw\"}},\"click\":{\"actionType\":\"click\", \"key\":\"VvtzNmkR8hrG8AzvTOGz4BRf0o30wKCEloxPgfvLElj1\", \"custom\":{\"advertLite\":\"AD8CNMKJdH8z_TI6OK3gt22QHTS4dWYqqC1DuhGiclvncnCh-WnNUljZbvGkFOnYNiNx4lO0NmA7Pz7jsw\"}},\"right_click\":{\"actionType\":\"right_click\", \"key\":\"VvtzNmkR8hrG8AzvTOGz4BRf0o30wKCEloxPgfvLElj1\", \"custom\":{\"advertLite\":\"AD8CNMKJdH8z_TI6OK3gt22QHTS4dWYqqC1DuhGiclvncnCh-WnNUljZbvGkFOnYNiNx4lO0NmA7Pz7jsw\"}},\"view\":{\"actionType\":\"view\", \"key\":\"VvtzNmkR8hrG8AzvTOGz4BRf0o30wKCEloxPgfvLElj1\"}}},{\"action\":{\"behavior\":\"BEHAVIOR_TYPE_REDIRECT\", \"link\":\"/product/kupalnik-razdelnyy-show-me-show-1565827878/?at=ywtAqK2R3IxE7q51IYyEk70F0pOBRnH0Mg7zPcojMAvk\"},\"alt\":\"Купальник раздельный Show Me Show Рекомендуем для вас\",\"isAdult\":false,\"items\":[{\"type\":\"image\", \"image\":{\"link\":\"https://cdn1.ozone.ru/s3/multimedia-1-c/7564289772.jpg\", \"contentMode\":\"SCALE_ASPECT_FILL\"}}],\"link\":\"/product/kupalnik-razdelnyy-show-me-show-1565827878/?at=ywtAqK2R3IxE7q51IYyEk70F0pOBRnH0Mg7zPcojMAvk\",\"shouldBlur\":false,\"skuId\":\"1565827878\",\"state\":[{\"type\":\"priceV2\", \"priceV2\":{\"price\":[{\"text\":\"1 665 ₽\", \"textStyle\":\"PRICE\"}, {\"text\":\"5 700 ₽\", \"textStyle\":\"ORIGINAL_PRICE\"}], \"discount\":\"−70%\", \"priceStyle\":{\"styleType\":\"SALE_PRICE\", \"gradient\":{\"startColor\":\"#F1117E\", \"endColor\":\"#F1117E\"}}, \"preset\":\"SIZE_500\", \"paddingBottom\":\"PADDING_200\"}},{\"type\":\"textAtom\", \"textAtom\":{\"text\":\"3 шт осталось\", \"textStyle\":\"tsBodyControl400Small\", \"textColor\":\"textAccent\", \"maxLines\":1, \"testInfo\":{\"automatizationId\":\"tile-blackFridayStockbar\"}}},{\"type\":\"textAtom\", \"textAtom\":{\"text\":\"Купальник раздельный Show Me Show\", \"textStyle\":\"tsBodyL\", \"maxLines\":2, \"testInfo\":{\"automatizationId\":\"tile-name\"}}, \"id\":\"name\"}],\"trackingInfo\":{\"aux_click\":{\"actionType\":\"aux_click\", \"key\":\"ywtAqK2R3IxE7q51IYyEk70F0pOBRnH0Mg7zPcojMAvk\", \"custom\":{\"advertLite\":\"AD8CG9zy7Tt5vb0ZESbu_zR6FtJ5j0DP3LFtpiKfKv3p8kY0fR8147BM96r8yEPzGR8uq1r9mu0gAJ03GwY\"}},\"click\":{\"actionType\":\"click\", \"key\":\"ywtAqK2R3IxE7q51IYyEk70F0pOBRnH0Mg7zPcojMAvk\", \"custom\":{\"advertLite\":\"AD8CG9zy7Tt5vb0ZESbu_zR6FtJ5j0DP3LFtpiKfKv3p8kY0fR8147BM96r8yEPzGR8uq1r9mu0gAJ03GwY\"}},\"right_click\":{\"actionType\":\"right_click\", \"key\":\"ywtAqK2R3IxE7q51IYyEk70F0pOBRnH0Mg7zPcojMAvk\", \"custom\":{\"advertLite\":\"AD8CG9zy7Tt5vb0ZESbu_zR6FtJ5j0DP3LFtpiKfKv3p8kY0fR8147BM96r8yEPzGR8uq1r9mu0gAJ03GwY\"}},\"view\":{\"actionType\":\"view\", \"key\":\"ywtAqK2R3IxE7q51IYyEk70F0pOBRnH0Mg7zPcojMAvk\"}}},{\"action\":{\"behavior\":\"BEHAVIOR_TYPE_REDIRECT\", \"link\":\"/product/shorty-dlya-plavaniya-jk-wear-bsh-01-1562251045/?at=LZtlyVwZ2c1p2l1wFm59YV4twVnvK4TgNnwl5cxJwBzy\"},\"alt\":\"Шорты для плавания JK Wear BSH_01 Рекомендуем для вас\",\"isAdult\":false,\"items\":[{\"type\":\"image\", \"image\":{\"link\":\"https://cdn1.ozone.ru/s3/multimedia-1-8/7292684600.jpg\", \"contentMode\":\"SCALE_ASPECT_FILL\"}}],\"link\":\"/product/shorty-dlya-plavaniya-jk-wear-bsh-01-1562251045/?at=LZtlyVwZ2c1p2l1wFm59YV4twVnvK4TgNnwl5cxJwBzy\",\"shouldBlur\":false,\"skuId\":\"1562251045\",\"state\":[{\"type\":\"priceV2\", \"priceV2\":{\"price\":[{\"text\":\"497 ₽\", \"textStyle\":\"PRICE\"}, {\"text\":\"2 990 ₽\", \"textStyle\":\"ORIGINAL_PRICE\"}], \"discount\":\"−83%\", \"priceStyle\":{\"styleType\":\"SALE_PRICE\", \"gradient\":{\"startColor\":\"#F1117E\", \"endColor\":\"#F1117E\"}}, \"preset\":\"SIZE_500\", \"paddingBottom\":\"PADDING_200\"}},{\"type\":\"textAtom\", \"textAtom\":{\"text\":\"149 шт осталось\", \"textStyle\":\"tsBodyControl400Small\", \"textColor\":\"textAccent\", \"maxLines\":1, \"testInfo\":{\"automatizationId\":\"tile-blackFridayStockbar\"}}},{\"type\":\"textAtom\", \"textAtom\":{\"text\":\"Шорты для плавания JK Wear BSH_01\", \"textStyle\":\"tsBodyL\", \"maxLines\":2, \"testInfo\":{\"automatizationId\":\"tile-name\"}}, \"id\":\"name\"}],\"trackingInfo\":{\"aux_click\":{\"actionType\":\"aux_click\", \"key\":\"LZtlyVwZ2c1p2l1wFm59YV4twVnvK4TgNnwl5cxJwBzy\", \"custom\":{\"advertLite\":\"AD8CL2no8I6L8DZ2ElU_RAdA5BgFSGYjAqtaNA1GtZ_5_dZPBAXaHHh7DEvgAn0I-fE7OjhmpnjqxtUE624\"}},\"click\":{\"actionType\":\"click\", \"key\":\"LZtlyVwZ2c1p2l1wFm59YV4twVnvK4TgNnwl5cxJwBzy\", \"custom\":{\"advertLite\":\"AD8CL2no8I6L8DZ2ElU_RAdA5BgFSGYjAqtaNA1GtZ_5_dZPBAXaHHh7DEvgAn0I-fE7OjhmpnjqxtUE624\"}},\"right_click\":{\"actionType\":\"right_click\", \"key\":\"LZtlyVwZ2c1p2l1wFm59YV4twVnvK4TgNnwl5cxJwBzy\", \"custom\":{\"advertLite\":\"AD8CL2no8I6L8DZ2ElU_RAdA5BgFSGYjAqtaNA1GtZ_5_dZPBAXaHHh7DEvgAn0I-fE7OjhmpnjqxtUE624\"}},\"view\":{\"actionType\":\"view\", \"key\":\"LZtlyVwZ2c1p2l1wFm59YV4twVnvK4TgNnwl5cxJwBzy\"}}}]},\"widgetOptions\":{\"imageAlign\":\"\", \"keepScrollPosition\":false}}","column-3474022-default-1":"{}","row-3474023-default-1":"{}"},"browser":{"ip":"46.246.9.220","isDesktop":true,"platform":"desktop","browser":"Mozilla/5.0 (Windows NT 10.0; Win64; x64) AppleWebKit/537.36 (KHTML, like Gecko) Chrome/120.0.0.0 Safari/537.36","prevLocation":"https://www.ozon.ru/product/kupalnik-razdelnyy-opasnaya-2154030454/?__rr=1&abt_att=1","useSW":true,"trackResources":true,"webp":true,"device":"desktop","age":"modern","cspNonce":"59de81c4-eb14-4efe-926b-512a032a8fa9","family":"Chrome","majorVersion":120,"cdnImgHostname":"ir.ozone.ru","cdnVideoHostname":"v-1.ozone.ru","cdnOriginalImgHostname":"io.ozone.ru","cdnStaticHostname":"st.ozone.ru","avif":true},"client":{"platform":"desktop","marketplaceDomain":"ozon.ru"},"layoutTrackingInfo":"{\"layoutId\":1689, \"layoutVersion\":176, \"pageType\":\"search_suggestions\", \"ruleId\":1485, \"deviceType\":\"desktop\", \"platform\":\"site\", \"templateType\":\"desktop\", \"marketplaceId\":1, \"requestId\":\"5b8338cb253b2154dc8e2f4813de9c4d\", \"userWwId\":1}","location":{"current":{"areaId":2,"areaType":4,"countryCode":"RUS","countryId":1,"fias":"0c5b2444-70a0-4932-980c-b4dc0d3f02b5","fullName":"Москва","timeZoneUtcname":"UTC+3","geoCoordinate":{},"uid":"0c5b2444-70a0-4932-980c-b4dc0d3f02b5"}},"seo":{"link":[{"href":"https://www.ozon.ru/page/json/v2","rel":"canonical"}]},"shared":"{\"context\":\"ozon\"}","segments":[1],"pageInfo":{"url":"/searchSuggestions/search/?from_global=true&text=","layoutId":1689,"layoutVersion":176,"pageType":"search_suggestions","ruleId":1485,"referer":"https://www.ozon.ru/product/kupalnik-razdelnyy-opasnaya-2154030454/?__rr=1&abt_att=1","pageTypeTracking":"search_suggestions"},"trackingPayloads":{"0RRM1-awwK_nJPoCYcZ1YxdjTZhAIqk6":"{\"layoutId\":1689, \"layoutVersion\":176, \"pageType\":\"search_suggestions\", \"ruleId\":1485, \"deviceType\":\"desktop\", \"platform\":\"site\", \"templateType\":\"desktop\", \"marketplaceId\":1, \"requestId\":\"5b8338cb253b2154dc8e2f4813de9c4d\", \"userWwId\":1}"},"pageToken":"0RRM1-awwK_nJPoCYcZ1YxdjTZhAIqk6","serverTiming":[{"duration":4,"name":"Resolve"},{"duration":177,"name":"Widgets"},{"duration":183,"name":"Total"},{"duration":183,"name":"ComposerTotal"},{"duration":1,"name":"ComposerInternal"}],"userToken":"15RM1MMoD3W9pUhhkMqLA_klOiEvx5dq","experimentsConfig":{"isModern":true,"swDisableReinitSPA":true,"useNewSwPath":true,"entrypointCacheControl":true,"cpmTrackerEnabled":true,"prerenderCartPageSW":true,"enableSpeculationRules":true,"mergeUrlLogger":true,"isTrinityEvent":true,"trackMediaPlayerMetricsRum4":true,"newPaginationRum4":true,"prerenderCheckoutSW":true,"disableVersionFallback":true,"trackImagesRum4":true,"enableTrackerInfoLogs":true,"enableVersionFallbackLogs":true,"prerenderSuggestions":true,"trackLcpElement":true,"entrypointPrerenderHome":true,"imgPixelatedRender":true,"disableSendWidgetViewCE":true,"allyMode":true,"withPerformanceMarks":true,"fingerprinting":true,"detectHeadlessRum4":true,"newOrderDone":true,"useEntrypointPageJson":true,"usePreloadImagesPDPGallery":true,"lowerGalleryImageQuality":true,"alternativeCdnImages":true,"s3PublicPath":true,"disableProductClickEvent":true,"enableDevtools":true,"prefetchAssetsSW":true,"earlyHintsEnabled":true,"linkAsyncWidgets":true,"useCrossorigin":true,"isCdnFonts":true,"enableSWCaching":true,"trackMessengerRum4":true,"disableWidgetTracking":true,"enableTrackerLogs":true,"fastDeliveryDeploy":true,"prerenderHomePageSW":true,"isStickySearchbar":true,"gtmDelay2000":true},"requestID":"5b8338cb253b2154dc8e2f4813de9c4d","verticalInfo":{"cms":{"publicPath":"https://st.ozone.ru/s3/assets-27147/114adeb3/","initial":["microfront/catalog-menu-cms-uw.js"],"experimentsConfig":null},"common":{"publicPath":"https://st.ozone.ru/assets/a188a2a7/","initial":["detached/common/entry.common.js"],"experimentsConfig":null},"products":{"publicPath":"https://st.ozone.ru/assets/a188a2a7/","initial":["detached/navi/entry.products.js"],"experimentsConfig":null},"layout":{"publicPath":"https://st.ozone.ru/assets/a188a2a7/","initial":[],"experimentsConfig":null},"search":{"publicPath":"https://st.ozone.ru/assets/a188a2a7/","initial":["detached/search/entry.search.js"],"experimentsConfig":null}},"resolveParams":{"cdn_img_hostname":"ir.ozone.ru","cdn_video_review_hostname":"vr-1.ozone.ru","cdn_static_hostname":"st.ozone.ru","cdn_video_pdp_hostname":"vp-1.ozone.ru","request.url.domain.level2":"ozon.ru","cdn_video_tile_hostname":"vt-1.ozone.ru","current.time":"2025-08-13T05:25:08.525683206Z","cdn_original_img_hostname":"io.ozone.ru","cdn_video_hostname":"v-1.ozone.ru"}}